django_settings_export.py
django_settings_export-1.0.6.dist-info/DESCRIPTION.rst
django_settings_export-1.0.6.dist-info/METADATA
django_settings_export-1.0.6.dist-info/metadata.json
django_settings_export-1.0.6.dist-info/RECORD
django_settings_export-1.0.6.dist-info/top_level.txt
django_settings_export-1.0.6.dist-info/WHEEL
