Metadata-Version: 2.0
Name: django-settings-export
Version: 1.0.6
Summary: This Django app allows you to export certain settings to your templates.
Home-page: https://github.com/jkbrzt/django-settings-export
Author: Jakub Roztocil
Author-email: jakub@roztocil.co
License: BSD
Platform: UNKNOWN
Classifier: Intended Audience :: Developers
Classifier: Programming Language :: Python
Classifier: Programming Language :: Python :: 2
Classifier: Programming Language :: Python :: 3
Requires-Dist: django
